smappy/__init__.py
smappy/smappy.py
smappy-0.2.16.dist-info/DESCRIPTION.rst
smappy-0.2.16.dist-info/METADATA
smappy-0.2.16.dist-info/RECORD
smappy-0.2.16.dist-info/WHEEL
smappy-0.2.16.dist-info/metadata.json
smappy-0.2.16.dist-info/top_level.txt
