Metadata-Version: 2.0
Name: smappy
Version: 0.2.16
Summary: A python API wrapper for Smappee
Home-page: https://github.com/energieid/smappy
Author: EnergieID.be
Author-email: jan@energieid.be
License: MIT
Keywords: smappee data monitoring api
Platform: UNKNOWN
Classifier: Development Status :: 3 - Alpha
Classifier: Intended Audience :: Developers
Classifier: Topic :: Scientific/Engineering
Classifier: License :: OSI Approved :: MIT License
Classifier: Programming Language :: Python :: 3
Classifier: Programming Language :: Python :: 3.2
Classifier: Programming Language :: Python :: 3.3
Classifier: Programming Language :: Python :: 3.4
Classifier: Programming Language :: Python :: 3.5
Requires-Dist: requests
Requires-Dist: pytz
